telemulator3/__init__.py
telemulator3/api.py
telemulator3/dictionaryable.py
telemulator3/user.py
telemulator3/chat/__init__.py
telemulator3/chat/base.py
telemulator3/chat/channel.py
telemulator3/chat/group.py
telemulator3/chat/history.py
telemulator3/chat/keyboard.py
telemulator3/chat/member.py
telemulator3/chat/private.py
telemulator3/method/__init__.py
telemulator3/method/answerCallbackQuery.py
telemulator3/method/deleteMessage.py
telemulator3/method/editMessageCaption.py
telemulator3/method/editMessageReplyMarkup.py
telemulator3/method/editMessageText.py
telemulator3/method/forwardMessage.py
telemulator3/method/getChat.py
telemulator3/method/getChatAdministrators.py
telemulator3/method/getChatMember.py
telemulator3/method/getChatMemberCount.py
telemulator3/method/getFile.py
telemulator3/method/getMe.py
telemulator3/method/leaveChat.py
telemulator3/method/sendAudio.py
telemulator3/method/sendChatAction.py
telemulator3/method/sendDocument.py
telemulator3/method/sendMessage.py
telemulator3/method/sendPhoto.py
telemulator3/method/setWebhook.py
telemulator3/update/__init__.py
telemulator3/update/callback_query.py
telemulator3/update/markup.py
telemulator3/update/message.py
telemulator3-1.5.dist-info/LICENSE
telemulator3-1.5.dist-info/METADATA
telemulator3-1.5.dist-info/WHEEL
telemulator3-1.5.dist-info/top_level.txt
telemulator3-1.5.dist-info/RECORD
