Metadata-Version: 2.1
Name: telemulator3
Version: 1.5
Summary: Mocked Telegram Bot API elements for unit tests of a bot based on the pyTelegramBotAPI library.
Home-page: https://github.com/vb64/telemulator3
Author: Vitaly Bogomolov
Author-email: mail@vitaly-bogomolov.ru
Project-URL: Bug Tracker, https://github.com/vb64/telemulator3/issues
Classifier: Programming Language :: Python :: 3
Classifier: License :: OSI Approved :: MIT License
Classifier: Operating System :: OS Independent
Requires-Python: >=3.7
License-File: LICENSE
Requires-Dist: pyTelegramBotAPI (<=4.11.0)
